zeeland/__init__.py
zeeland/core.py
zeeland/logger.py
zeeland/singleton.py
zeeland/version_checker.py
zeeland-0.3.0.dist-info/LICENSE
zeeland-0.3.0.dist-info/METADATA
zeeland-0.3.0.dist-info/WHEEL
zeeland-0.3.0.dist-info/RECORD
