Metadata-Version: 2.1
Name: zeeland
Version: 0.3.0
Summary: zeeland frameworks core infra
Home-page: https://github.com/Undertone0809/zeeland
License: MIT
Author: zeeland
Author-email: zeeland4work@gmail.com
Requires-Python: >=3.8,<4.0
Classifier: License :: OSI Approved :: MIT License
Classifier: Programming Language :: Python :: 3
Classifier: Programming Language :: Python :: 3.8
Classifier: Programming Language :: Python :: 3.9
Classifier: Programming Language :: Python :: 3.10
Classifier: Programming Language :: Python :: 3.11
Classifier: Programming Language :: Python :: 3.12
Project-URL: Repository, https://github.com/Undertone0809/zeeland
